src/__init__.py
src/ai_code_review.py
src/generate_code_review_context.py
src/model_config.json
src/server.py
task_list_code_review_mcp-0.2.1.dist-info/METADATA
task_list_code_review_mcp-0.2.1.dist-info/WHEEL
task_list_code_review_mcp-0.2.1.dist-info/entry_points.txt
task_list_code_review_mcp-0.2.1.dist-info/RECORD
