Metadata-Version: 2.4
Name: task-list-code-review-mcp
Version: 0.2.1
Summary: MCP server for AI-powered task list code reviews with PRD context
Project-URL: Homepage, https://github.com/nicobailon/task-list-code-review-mcp
Project-URL: Repository, https://github.com/nicobailon/task-list-code-review-mcp
Project-URL: Issues, https://github.com/nicobailon/task-list-code-review-mcp/issues
Author-email: Nico Bailon <nico604@pm.me>
License: MIT
Classifier: Development Status :: 4 - Beta
Classifier: Intended Audience :: Developers
Classifier: License :: OSI Approved :: MIT License
Classifier: Programming Language :: Python :: 3
Classifier: Programming Language :: Python :: 3.8
Classifier: Programming Language :: Python :: 3.9
Classifier: Programming Language :: Python :: 3.10
Classifier: Programming Language :: Python :: 3.11
Classifier: Programming Language :: Python :: 3.12
Requires-Python: >=3.8
Requires-Dist: fastmcp>=0.1.0
Requires-Dist: google-genai>=0.1.0
Requires-Dist: python-dotenv>=1.0.0
Provides-Extra: dev
Requires-Dist: black; extra == 'dev'
Requires-Dist: flake8; extra == 'dev'
Requires-Dist: isort; extra == 'dev'
Requires-Dist: pytest-asyncio>=0.21.0; extra == 'dev'
Requires-Dist: pytest-mock>=3.0.0; extra == 'dev'
Requires-Dist: pytest>=7.0.0; extra == 'dev'
